funniest/__init__.py
funniest/lib1.py
mkc_funniest-0.3.dist-info/METADATA
mkc_funniest-0.3.dist-info/WHEEL
mkc_funniest-0.3.dist-info/top_level.txt
mkc_funniest-0.3.dist-info/RECORD
