Metadata-Version: 2.1
Name: mkc-funniest
Version: 0.3
Summary: The funniest joke in the world
Home-page: http://github.com/storborg/funniest
Author: Michael Chen
Author-email: flyingcircus@example.com
License: MIT
Platform: UNKNOWN
